django_mapit-3.0.data/scripts/mapit_make_css
mapit/__init__.py
mapit/admin.py
mapit/context_processors.py
mapit/geometryserialiser.py
mapit/iterables.py
mapit/models.py
mapit/ratelimitcache.py
mapit/shortcuts.py
mapit/urls.py
mapit/utils.py
mapit/countries/__init__.py
mapit/fixtures/ireland.json
mapit/management/__init__.py
mapit/management/command_utils.py
mapit/management/find_parents.py
mapit/management/commands/__init__.py
mapit/management/commands/mapit_delete_areas_from_new_generation.py
mapit/management/commands/mapit_generation_activate.py
mapit/management/commands/mapit_generation_create.py
mapit/management/commands/mapit_generation_deactivate.py
mapit/management/commands/mapit_generation_raise_on_current_areas.py
mapit/management/commands/mapit_import.py
mapit/management/commands/mapit_import_area_unions.py
mapit/management/commands/mapit_import_postal_codes.py
mapit/management/commands/mapit_make_fusion_csv.py
mapit/management/commands/mapit_print_areas.py
mapit/middleware/__init__.py
mapit/middleware/view_error.py
mapit/migrations/0001_initial.py
mapit/migrations/0002_auto_20141218_1615.py
mapit/migrations/0003_auto_20161205_1050.py
mapit/migrations/0004_add_country_m2m.py
mapit/migrations/__init__.py
mapit/sql/postcode.sql
mapit/static/mapit/css/mapit.css
mapit/static/mapit/css/mapit.css.map
mapit/static/mapit/img/favicon.ico
mapit/static/mapit/img/footer-logo-openpolis.png
mapit/static/mapit/img/footer-logo-openpolis@2x.png
mapit/static/mapit/img/mysociety-bloom.png
mapit/static/mapit/img/mysociety-bloom@2.png
mapit/static/mapit/img/mysociety-logo.png
mapit/static/mapit/img/mysociety-logo.svg
mapit/static/mapit/img/mysociety-logo@2.png
mapit/static/mapit/img/openpolis-bloom.png
mapit/static/mapit/img/openpolis-bloom@2x.png
mapit/static/mapit/img/openpolis-tool.png
mapit/static/mapit/img/openpolis-tool@2x.png
mapit/static/mapit/img/tree-branch.png
mapit/static/mapit/img/tree-last.png
mapit/static/mapit/img/tree-upright.png
django_mapit-3.0.dist-info/LICENSE.txt
django_mapit-3.0.dist-info/METADATA
django_mapit-3.0.dist-info/WHEEL
django_mapit-3.0.dist-info/top_level.txt
django_mapit-3.0.dist-info/RECORD
