Metadata-Version: 2.1
Name: django-mapit
Version: 3.0
Summary: A web service for mapping postcodes and points to current or past administrative area information and polygons.
Home-page: https://github.com/mysociety/mapit
Author: mySociety
Author-email: mapit@mysociety.org
License: LICENSE.txt
Platform: UNKNOWN
Classifier: Development Status :: 5 - Production/Stable
Classifier: Environment :: Web Environment
Classifier: Framework :: Django
Classifier: License :: OSI Approved :: GNU Affero General Public License v3
Classifier: Intended Audience :: Developers
Classifier: Programming Language :: Python
Classifier: Programming Language :: Python :: 2
Classifier: Programming Language :: Python :: 3
Classifier: Topic :: Database :: Front-Ends
Classifier: Topic :: Internet :: WWW/HTTP
Classifier: Topic :: Scientific/Engineering :: GIS
Requires-Dist: Django (>=1.11.2)
Requires-Dist: libsass
Requires-Dist: psycopg2
Requires-Dist: PyYAML
Requires-Dist: Shapely
Requires-Dist: six
Requires-Dist: uk-postcode-utils
